find_min/__init__.py
find_min/find_min.py
find_min/sample/__init__.py
find_min/sample/sample_file.py
find_min/sample/samples.py
find_min/tests/__init__.py
find_min/tests/test_find_min.py
findMin-11.0.0.dist-info/LICENSE
findMin-11.0.0.dist-info/METADATA
findMin-11.0.0.dist-info/WHEEL
findMin-11.0.0.dist-info/top_level.txt
findMin-11.0.0.dist-info/RECORD
