Metadata-Version: 2.1
Name: findMin
Version: 11.0.0
Summary: Find the minimum in array using as few comparisons as possible
Home-page: https://github.com/rafey.husain/findMin
Author: Syed Rafey Husain
Author-email: rafey.husain@outlook.com
License: UNKNOWN
Platform: UNKNOWN
Classifier: Programming Language :: Python :: 3
Classifier: License :: OSI Approved :: MIT License
Classifier: Operating System :: OS Independent
Requires-Python: >=3.6
